{
	"id": "feed7373-4b92-4bef-a6bc-bd3e76c0f1f0",
	"name": "Env_for_second_coll",
	"values": [
		{
			"key": "id",
			"value": "5ac1f09a60edb54701c767da",
			"enabled": true
		},
		{
			"key": "direction",
			"value": "bee33a4c-e0cf-4f2c-80b5-93ccab966e46",
			"enabled": true
		},
		{
			"key": "number",
			"value": "39804",
			"enabled": true
		},
		{
			"key": "date_created",
			"value": "669772800000",
			"enabled": true
		},
		{
			"key": "date_due",
			"value": "08 August 1985",
			"enabled": true
		},
		{
			"key": "date_supply",
			"value": "340329600000",
			"enabled": true
		},
		{
			"key": "comment",
			"value": "Esse nisi dolore nisi velit ea cillum deserunt. Sunt aliquip esse elit irure eiusmod sunt commodo sint cupidatat aliqua velit elit amet ut. Dolor esse ad ad non adipisicing culpa id voluptate do.",
			"enabled": true
		}
	],
	"_postman_variable_scope": "environment",
	"_postman_exported_at": "2019-10-07T12:25:35.887Z",
	"_postman_exported_using": "Postman/7.8.0"
}